.gitignore
.gitmodules
CMakeLists.txt
CMakeLists.txt.gtest.in
LICENSE
MANIFEST.in
README.md
README.pypi
setup.cfg
setup.py
test-requirements.txt
versioneer.py
.circleci/config.yml
deps/RandomX/.git
deps/RandomX/.gitignore
deps/RandomX/CMakeLists.txt
deps/RandomX/LICENSE
deps/RandomX/README.md
deps/RandomX/randomx.sln
deps/RandomX/audits/Report-Kudelski.pdf
deps/RandomX/audits/Report-Quarkslab.pdf
deps/RandomX/audits/Report-TrailOfBits.pdf
deps/RandomX/audits/Report-X41.pdf
deps/RandomX/doc/configuration.md
deps/RandomX/doc/design.md
deps/RandomX/doc/program.asm
deps/RandomX/doc/specs.md
deps/RandomX/src/aes_hash.cpp
deps/RandomX/src/aes_hash.hpp
deps/RandomX/src/allocator.cpp
deps/RandomX/src/allocator.hpp
deps/RandomX/src/argon2.h
deps/RandomX/src/argon2_avx2.c
deps/RandomX/src/argon2_core.c
deps/RandomX/src/argon2_core.h
deps/RandomX/src/argon2_ref.c
deps/RandomX/src/argon2_ssse3.c
deps/RandomX/src/assembly_generator_x86.cpp
deps/RandomX/src/assembly_generator_x86.hpp
deps/RandomX/src/blake2_generator.cpp
deps/RandomX/src/blake2_generator.hpp
deps/RandomX/src/bytecode_machine.cpp
deps/RandomX/src/bytecode_machine.hpp
deps/RandomX/src/common.hpp
deps/RandomX/src/configuration.h
deps/RandomX/src/cpu.cpp
deps/RandomX/src/cpu.hpp
deps/RandomX/src/dataset.cpp
deps/RandomX/src/dataset.hpp
deps/RandomX/src/instruction.cpp
deps/RandomX/src/instruction.hpp
deps/RandomX/src/instruction_weights.hpp
deps/RandomX/src/instructions_portable.cpp
deps/RandomX/src/intrin_portable.h
deps/RandomX/src/jit_compiler.hpp
deps/RandomX/src/jit_compiler_a64.cpp
deps/RandomX/src/jit_compiler_a64.hpp
deps/RandomX/src/jit_compiler_a64_static.S
deps/RandomX/src/jit_compiler_a64_static.hpp
deps/RandomX/src/jit_compiler_fallback.hpp
deps/RandomX/src/jit_compiler_x86.cpp
deps/RandomX/src/jit_compiler_x86.hpp
deps/RandomX/src/jit_compiler_x86_static.S
deps/RandomX/src/jit_compiler_x86_static.asm
deps/RandomX/src/jit_compiler_x86_static.hpp
deps/RandomX/src/program.hpp
deps/RandomX/src/randomx.cpp
pyqrandomx.egg-info/PKG-INFO
pyqrandomx.egg-info/SOURCES.txt
pyqrandomx.egg-info/dependency_links.txt
pyqrandomx.egg-info/top_level.txt
